[{"url":"https://www.chess.com/game/live/5412276110","time_class":"blitz","end_time":1599504525,"rated":true,"white":{"username":"Shubh002","result":"resigned"},"black":{"username":"colemartin99","result":"win"}},{"url":"https://www.chess.com/game/live/5412358566","time_class":"blitz","end_time":1599505723,"rated":true,"white":{"username":"you656","result":"win"},"black":{"username":"colemartin99","result":"checkmated"}},{"url":"https://www.chess.com/game/live/5413874071","time_class":"blitz","end_time":1599533472,"rated":true,"white":{"username":"JDR33D","result":"resigned"},"black":{"username":"colemartin99","result":"win"}},{"url":"https://www.chess.com/game/live/5413916761","time_class":"blitz","end_time":1599534257,"rated":true,"white":{"username":"colemartin99","result":"win"},"black":{"username":"psikopatruletci","result":"checkmated"}},{"url":"https://www.chess.com/game/live/5423101126","time_class":"blitz","end_time":1599695180,"rated":true,"white":{"username":"colemartin99","result":"win"},"black":{"username":"volatiliteriter","result":"resigned"}},{"url":"https://www.chess.com/game/live/5423127021","time_class":"blitz","end_time":1599695438,"rated":true,"white":{"username":"colemartin99","result":"abandoned"},"black":{"username":"chronog7","result":"win"}},{"url":"https://www.chess.com/game/live/5423149547","time_class":"blitz","end_time":1599696313,"rated":true,"white":{"username":"murthy9857","result":"checkmated"},"black":{"username":"colemartin99","result":"win"}},{"url":"https://www.chess.com/game/live/5430007266","time_class":"rapid","end_time":1599827438,"rated":true,"white":{"username":"colemartin99","result":"checkmated"},"black":{"username":"GhassanAlii","result":"win"}},{"url":"https://www.chess.com/game/live/5437454488","time_class":"rapid","end_time":1599957826,"rated":true,"white":{"username":"gcenac","result":"checkmated"},"black":{"username":"colemartin99","result":"win"}},{"url":"https://www.chess.com/game/live/5437465523","time_class":"rapid","end_time":1599959037,"rated":true,"white":{"username":"prrr_45","result":"abandoned"},"black":{"username":"colemartin99","result":"win"}},{"url":"https://www.chess.com/game/live/5437570742","time_class":"rapid","end_time":1599960820,"rated":true,"white":{"username":"colemartin99","result":"win"},"black":{"username":"Theobeey","result":"resigned"}},{"url":"https://www.chess.com/game/live/5441025490","time_class":"rapid","end_time":1600024686,"rated":true,"white":{"username":"Manupadiyam","result":"win"},"black":{"username":"colemartin99","result":"abandoned"}},{"url":"https://www.chess.com/game/live/5441662474","time_class":"rapid","end_time":1600035624,"rated":true,"white":{"username":"colemartin99","result":"abandoned"},"black":{"username":"Tribune2000","result":"win"}},{"url":"https://www.chess.com/game/live/5442077025","time_class":"rapid","end_time":1600044251,"rated":true,"white":{"username":"geeteebee","result":"win"},"black":{"username":"colemartin99","result":"resigned"}},{"url":"https://www.chess.com/game/live/5451823850","time_class":"rapid","end_time":1600223372,"rated":true,"white":{"username":"mlisto4525","result":"win"},"black":{"username":"colemartin99","result":"checkmated"}},{"url":"https://www.chess.com/game/live/5451851294","time_class":"rapid","end_time":1600224395,"rated":true,"white":{"username":"colemartin99","result":"win"},"black":{"username":"jpkynusty","result":"checkmated"}},{"url":"https://www.chess.com/game/live/5459918704","time_class":"rapid","end_time":1600370872,"rated":true,"white":{"username":"colemartin99","result":"win"},"black":{"username":"Mst60","result":"checkmated"}},{"url":"https://www.chess.com/game/live/5459954205","time_class":"rapid","end_time":1600371152,"rated":true,"white":{"username":"colemartin99","result":"checkmated"},"black":{"username":"d4chess7","result":"win"}},{"url":"https://www.chess.com/game/live/5460122865","time_class":"rapid","end_time":1600373710,"rated":true,"white":{"username":"colemartin99","result":"abandoned"},"black":{"username":"Sigimigi_minto","result":"win"}},{"url":"https://www.chess.com/game/live/5465063976","time_class":"rapid","end_time":1600463800,"rated":true,"white":{"username":"mgehlot15","result":"checkmated"},"black":{"username":"colemartin99","result":"win"}},{"url":"https://www.chess.com/game/live/5475038419","time_class":"rapid","end_time":1600659679,"rated":true,"white":{"username":"tdogsixtynine","result":"resigned"},"black":{"username":"colemartin99","result":"win"}},{"url":"https://www.chess.com/game/live/5520518674","time_class":"rapid","end_time":1601501074,"rated":true,"white":{"username":"colemartin99","result":"abandoned"},"black":{"username":"brammetje166","result":"win"}}]