[{"url":"https://www.chess.com/game/live/5873039971","time_class":"rapid","end_time":1606949751,"rated":true,"white":{"username":"Drjaykill","result":"resigned"},"black":{"username":"colemartin99","result":"win"}},{"url":"https://www.chess.com/game/live/5887531175","time_class":"rapid","end_time":1607112974,"rated":true,"white":{"username":"colemartin99","result":"win"},"black":{"username":"burak_harekat","result":"resigned"}},{"url":"https://www.chess.com/game/live/5889013161","time_class":"rapid","end_time":1607127168,"rated":true,"white":{"username":"dirtbag33","result":"win"},"black":{"username":"colemartin99","result":"checkmated"}},{"url":"https://www.chess.com/game/live/5894944723","time_class":"rapid","end_time":1607196225,"rated":true,"white":{"username":"colemartin99","result":"win"},"black":{"username":"BadBoyOfChess50","result":"resigned"}},{"url":"https://www.chess.com/game/live/5895032135","time_class":"rapid","end_time":1607197412,"rated":true,"white":{"username":"colemartin99","result":"stalemate"},"black":{"username":"itamar21","result":"stalemate"}},{"url":"https://www.chess.com/game/live/5911262689","time_class":"rapid","end_time":1607373324,"rated":true,"white":{"username":"MangoCrunk","result":"resigned"},"black":{"username":"colemartin99","result":"win"}},{"url":"https://www.chess.com/game/live/5911321996","time_class":"rapid","end_time":1607374552,"rated":true,"white":{"username":"colemartin99","result":"stalemate"},"black":{"username":"anisri201099","result":"stalemate"}},{"url":"https://www.chess.com/game/live/5911482625","time_class":"rapid","end_time":1607375682,"rated":true,"white":{"username":"KMD0123","result":"win"},"black":{"username":"colemartin99","result":"resigned"}},{"url":"https://www.chess.com/game/live/5914259212","time_class":"rapid","end_time":1607406954,"rated":true,"white":{"username":"dariogeremia","result":"resigned"},"black":{"username":"colemartin99","result":"win"}},{"url":"https://www.chess.com/game/live/5914301991","time_class":"rapid","end_time":1607407519,"rated":true,"white":{"username":"colemartin99","result":"win"},"black":{"username":"Artemis_Temn1k","result":"checkmated"}},{"url":"https://www.chess.com/game/live/5914339991","time_class":"rapid","end_time":1607408087,"rated":true,"white":{"username":"dookiepants69","result":"checkmated"},"black":{"username":"colemartin99","result":"win"}},{"url":"https://www.chess.com/game/live/5914385917","time_class":"rapid","end_time":1607409293,"rated":true,"white":{"username":"colemartin99","result":"win"},"black":{"username":"Xiao-Long-Bao","result":"checkmated"}},{"url":"https://www.chess.com/game/live/5919654264","time_class":"rapid","end_time":1607462796,"rated":true,"white":{"username":"nandet","result":"resigned"},"black":{"username":"colemartin99","result":"win"}},{"url":"https://www.chess.com/game/live/5925912762","time_class":"rapid","end_time":1607534348,"rated":true,"white":{"username":"ace0074012","result":"win"},"black":{"username":"colemartin99","result":"timeout"}},{"url":"https://www.chess.com/game/live/5933422478","time_class":"rapid","end_time":1607617423,"rated":true,"white":{"username":"colemartin99","result":"resigned"},"black":{"username":"pruthvi-nag","result":"win"}},{"url":"https://www.chess.com/game/live/5933732488","time_class":"rapid","end_time":1607620436,"rated":true,"white":{"username":"colemartin99","result":"win"},"black":{"username":"BUBBUZ","result":"checkmated"}},{"url":"https://www.chess.com/game/live/5933887789","time_class":"rapid","end_time":1607620738,"rated":true,"white":{"username":"colemartin99","result":"win"},"black":{"username":"Josephyle","result":"checkmated"}},{"url":"https://www.chess.com/game/live/5933961889","time_class":"rapid","end_time":1607621704,"rated":true,"white":{"username":"CJC1963","result":"resigned"},"black":{"username":"colemartin99","result":"win"}},{"url":"https://www.chess.com/game/live/5943356859","time_class":"rapid","end_time":1607719940,"rated":true,"white":{"username":"RegelUrbano","result":"abandoned"},"black":{"username":"colemartin99","result":"win"}},{"url":"https://www.chess.com/game/live/5943409619","time_class":"rapid","end_time":1607721005,"rated":true,"white":{"username":"colemartin99","result":"win"},"black":{"username":"Gstblack","result":"checkmated"}},{"url":"https://www.chess.com/game/live/5943524926","time_class":"rapid","end_time":1607721668,"rated":true,"white":{"username":"colemartin99","result":"checkmated"},"black":{"username":"Chermen9","result":"win"}},{"url":"https://www.chess.com/game/live/5958950718","time_class":"rapid","end_time":1607891484,"rated":false,"white":{"username":"colemartin99","result":"win"},"black":{"username":"nickbelk","result":"checkmated"}},{"url":"https://www.chess.com/game/live/5959058595","time_class":"rapid","end_time":1607891841,"rated":true,"white":{"username":"skoczeknac4","result":"checkmated"},"black":{"username":"colemartin99","result":"win"}},{"url":"https://www.chess.com/game/live/5960671717","time_class":"rapid","end_time":1607907987,"rated":true,"white":{"username":"maxpauly5","result":"win"},"black":{"username":"colemartin99","result":"resigned"}},{"url":"https://www.chess.com/game/live/5967664941","time_class":"rapid","end_time":1607982368,"rated":true,"white":{"username":"BarbudaBeluga","result":"resigned"},"black":{"username":"colemartin99","result":"win"}},{"url":"https://www.chess.com/game/live/5968138324","time_class":"rapid","end_time":1607986363,"rated":true,"white":{"username":"colemartin99","result":"win"},"black":{"username":"shikifujin0","result":"checkmated"}},{"url":"https://www.chess.com/game/live/5970109038","time_class":"rapid","end_time":1608010773,"rated":true,"white":{"username":"colemartin99","result":"checkmated"},"black":{"username":"miquilino","result":"win"}},{"url":"https://www.chess.com/game/live/5975349454","time_class":"rapid","end_time":1608064859,"rated":true,"white":{"username":"Shaulibetech","result":"abandoned"},"black":{"username":"colemartin99","result":"win"}},{"url":"https://www.chess.com/game/live/5975469616","time_class":"rapid","end_time":1608065646,"rated":true,"white":{"username":"shadypurp","result":"checkmated"},"black":{"username":"colemartin99","result":"win"}},{"url":"https://www.chess.com/game/live/5975539523","time_class":"rapid","end_time":1608066895,"rated":true,"white":{"username":"Yuillix","result":"timevsinsufficient"},"black":{"username":"colemartin99","result":"timevsinsufficient"}},{"url":"https://www.chess.com/game/live/5982610459","time_class":"rapid","end_time":1608142575,"rated":true,"white":{"username":"colemartin99","result":"win"},"black":{"username":"neil123321","result":"checkmated"}},{"url":"https://www.chess.com/game/live/5982797250","time_class":"rapid","end_time":1608145591,"rated":false,"white":{"username":"nickbelk","result":"win"},"black":{"username":"colemartin99","result":"checkmated"}},{"url":"https://www.chess.com/game/live/6006431372","time_class":"rapid","end_time":1608393916,"rated":true,"white":{"username":"colemartin99","result":"win"},"black":{"username":"nehaldesai2491","result":"checkmated"}},{"url":"https://www.chess.com/game/live/6007419274","time_class":"blitz","end_time":1608402134,"rated":true,"white":{"username":"NorthernStag","result":"checkmated"},"black":{"username":"colemartin99","result":"win"}},{"url":"https://www.chess.com/game/live/6007482688","time_class":"blitz","end_time":1608402617,"rated":true,"white":{"username":"colemartin99","result":"timeout"},"black":{"username":"Atharva045","result":"win"}},{"url":"https://www.chess.com/game/live/6007523482","time_class":"blitz","end_time":1608402882,"rated":true,"white":{"username":"santhoshpruthvi","result":"abandoned"},"black":{"username":"colemartin99","result":"win"}},{"url":"https://www.chess.com/game/live/6007561592","time_class":"blitz","end_time":1608403281,"rated":true,"white":{"username":"colemartin99","result":"timeout"},"black":{"username":"gowidaflow","result":"win"}},{"url":"https://www.chess.com/game/live/6007726310","time_class":"rapid","end_time":1608405036,"rated":true,"white":{"username":"colemartin99","result":"win"},"black":{"username":"Fratta88","result":"resigned"}},{"url":"https://www.chess.com/game/live/6007852188","time_class":"blitz","end_time":1608405703,"rated":true,"white":{"username":"colemartin99","result":"timeout"},"black":{"username":"mkbdahl","result":"win"}},{"url":"https://www.chess.com/game/live/6007984873","time_class":"blitz","end_time":1608406683,"rated":true,"white":{"username":"Garo9434","result":"win"},"black":{"username":"colemartin99","result":"resigned"}},{"url":"https://www.chess.com/game/live/6008033793","time_class":"blitz","end_time":1608406921,"rated":true,"white":{"username":"VeryRandomPerson","result":"win"},"black":{"username":"colemartin99","result":"resigned"}},{"url":"https://www.chess.com/game/live/6008045406","time_class":"blitz","end_time":1608407305,"rated":true,"white":{"username":"colemartin99","result":"checkmated"},"black":{"username":"yefer0609","result":"win"}},{"url":"https://www.chess.com/game/live/6009551544","time_class":"blitz","end_time":1608420681,"rated":true,"white":{"username":"MBenz25","result":"win"},"black":{"username":"colemartin99","result":"checkmated"}},{"url":"https://www.chess.com/game/live/6009585975","time_class":"rapid","end_time":1608421774,"rated":true,"white":{"username":"colemartin99","result":"win"},"black":{"username":"mattperrott13","result":"checkmated"}},{"url":"https://www.chess.com/game/live/6009981723","time_class":"blitz","end_time":1608425117,"rated":true,"white":{"username":"AbelSietecuatro","result":"win"},"black":{"username":"colemartin99","result":"checkmated"}},{"url":"https://www.chess.com/game/live/6010010025","time_class":"blitz","end_time":1608425453,"rated":true,"white":{"username":"mrsataniux","result":"win"},"black":{"username":"colemartin99","result":"resigned"}},{"url":"https://www.chess.com/game/live/6010035556","time_class":"blitz","end_time":1608426061,"rated":true,"white":{"username":"luccakrall","result":"checkmated"},"black":{"username":"colemartin99","result":"win"}},{"url":"https://www.chess.com/game/live/6010469616","time_class":"blitz","end_time":1608431489,"rated":true,"white":{"username":"colemartin99","result":"win"},"black":{"username":"leizarr","result":"resigned"}},{"url":"https://www.chess.com/game/live/6010499813","time_class":"blitz","end_time":1608432095,"rated":true,"white":{"username":"colemartin99","result":"timeout"},"black":{"username":"dleeruss","result":"win"}},{"url":"https://www.chess.com/game/live/6010556102","time_class":"blitz","end_time":1608432632,"rated":true,"white":{"username":"colemartin99","result":"win"},"black":{"username":"AndrewEccles15","result":"abandoned"}},{"url":"https://www.chess.com/game/live/6010579536","time_class":"blitz","end_time":1608432981,"rated":true,"white":{"username":"colemartin99","result":"win"},"black":{"username":"KingKongRomane","result":"checkmated"}},{"url":"https://www.chess.com/game/live/6011363150","time_class":"blitz","end_time":1608444434,"rated":true,"white":{"username":"Callthewizard","result":"timeout"},"black":{"username":"colemartin99","result":"win"}},{"url":"https://www.chess.com/game/live/6011393144","time_class":"blitz","end_time":1608444611,"rated":true,"white":{"username":"nilotic07","result":"win"},"black":{"username":"colemartin99","result":"abandoned"}},{"url":"https://www.chess.com/game/live/6011402802","time_class":"blitz","end_time":1608444897,"rated":true,"white":{"username":"Lavrenttie","result":"checkmated"},"black":{"username":"colemartin99","result":"win"}},{"url":"https://www.chess.com/game/live/6011423567","time_class":"blitz","end_time":1608445323,"rated":true,"white":{"username":"colemartin99","result":"timeout"},"black":{"username":"Seenu0P","result":"win"}},{"url":"https://www.chess.com/game/live/6011452199","time_class":"rapid","end_time":1608445691,"rated":true,"white":{"username":"Dhruv2021","result":"checkmated"},"black":{"username":"colemartin99","result":"win"}},{"url":"https://www.chess.com/game/live/6011477153","time_class":"rapid","end_time":1608446536,"rated":true,"white":{"username":"colemartin99","result":"checkmated"},"black":{"username":"ha69","result":"win"}},{"url":"https://www.chess.com/game/live/6015930362","time_class":"blitz","end_time":1608491631,"rated":true,"white":{"username":"colemartin99","result":"win"},"black":{"username":"Jainnikh3011","result":"checkmated"}},{"url":"https://www.chess.com/game/live/6016471945","time_class":"blitz","end_time":1608495718,"rated":true,"white":{"username":"f3xer","result":"resigned"},"black":{"username":"colemartin99","result":"win"}},{"url":"https://www.chess.com/game/live/6016478422","time_class":"blitz","end_time":1608496101,"rated":true,"white":{"username":"u06111964","result":"win"},"black":{"username":"colemartin99","result":"checkmated"}},{"url":"https://www.chess.com/game/live/6016539313","time_class":"blitz","end_time":1608496637,"rated":true,"white":{"username":"colemartin99","result":"resigned"},"black":{"username":"Christian4000","result":"win"}},{"url":"https://www.chess.com/game/live/6019416366","time_class":"blitz","end_time":1608529125,"rated":true,"white":{"username":"colemartin99","result":"timeout"},"black":{"username":"abdelrhmansayed","result":"win"}},{"url":"https://www.chess.com/game/live/6025937161","time_class":"blitz","end_time":1608591853,"rated":true,"white":{"username":"mar7308","result":"checkmated"},"black":{"username":"colemartin99","result":"win"}},{"url":"https://www.chess.com/game/live/6025946899","time_class":"blitz","end_time":1608592191,"rated":true,"white":{"username":"yamil1818","result":"win"},"black":{"username":"colemartin99","result":"timeout"}},{"url":"https://www.chess.com/game/live/6025982202","time_class":"blitz","end_time":1608592473,"rated":true,"white":{"username":"colemartin99","result":"checkmated"},"black":{"username":"richardmitch","result":"win"}},{"url":"https://www.chess.com/game/live/6026414353","time_class":"blitz","end_time":1608596808,"rated":true,"white":{"username":"colemartin99","result":"win"},"black":{"username":"jparrilla","result":"checkmated"}},{"url":"https://www.chess.com/game/live/6026437740","time_class":"blitz","end_time":1608597247,"rated":true,"white":{"username":"jorgesrs27","result":"win"},"black":{"username":"colemartin99","result":"checkmated"}},{"url":"https://www.chess.com/game/live/6026480602","time_class":"blitz","end_time":1608597584,"rated":true,"white":{"username":"freddberg","result":"resigned"},"black":{"username":"colemartin99","result":"win"}},{"url":"https://www.chess.com/game/live/6026503026","time_class":"blitz","end_time":1608597883,"rated":true,"white":{"username":"fisiobaf","result":"abandoned"},"black":{"username":"colemartin99","result":"win"}},{"url":"https://www.chess.com/game/live/6026548523","time_class":"blitz","end_time":1608598206,"rated":true,"white":{"username":"colemartin99","result":"win"},"black":{"username":"eriely","result":"resigned"}},{"url":"https://www.chess.com/game/live/6026555599","time_class":"blitz","end_time":1608598600,"rated":true,"white":{"username":"colemartin99","result":"checkmated"},"black":{"username":"jabob1999","result":"win"}},{"url":"https://www.chess.com/game/live/6027589917","time_class":"blitz","end_time":1608611557,"rated":true,"white":{"username":"jatin_rohilla","result":"win"},"black":{"username":"colemartin99","result":"timeout"}},{"url":"https://www.chess.com/game/live/6027620031","time_class":"rapid","end_time":1608611847,"rated":true,"white":{"username":"colemartin99","result":"win"},"black":{"username":"harrisonkennedy","result":"resigned"}},{"url":"https://www.chess.com/game/live/6027651668","time_class":"rapid","end_time":1608613153,"rated":true,"white":{"username":"martinovichev","result":"stalemate"},"black":{"username":"colemartin99","result":"stalemate"}},{"url":"https://www.chess.com/game/live/6027746915","time_class":"blitz","end_time":1608613594,"rated":true,"white":{"username":"deividasdevd","result":"win"},"black":{"username":"colemartin99","result":"timeout"}},{"url":"https://www.chess.com/game/live/6031838141","time_class":"blitz","end_time":1608657641,"rated":true,"white":{"username":"colemartin99","result":"timevsinsufficient"},"black":{"username":"Harleen07","result":"timevsinsufficient"}},{"url":"https://www.chess.com/game/live/6031888339","time_class":"blitz","end_time":1608657901,"rated":true,"white":{"username":"colemartin99","result":"checkmated"},"black":{"username":"chlipak","result":"win"}},{"url":"https://www.chess.com/game/live/6032290860","time_class":"blitz","end_time":1608661137,"rated":true,"white":{"username":"Solitaris","result":"timeout"},"black":{"username":"colemartin99","result":"win"}},{"url":"https://www.chess.com/game/live/6032346567","time_class":"blitz","end_time":1608661446,"rated":true,"white":{"username":"colemartin99","result":"checkmated"},"black":{"username":"Taygrant","result":"win"}},{"url":"https://www.chess.com/game/live/6032387640","time_class":"rapid","end_time":1608662311,"rated":true,"white":{"username":"colemartin99","result":"win"},"black":{"username":"JRG22_3","result":"timeout"}},{"url":"https://www.chess.com/game/live/6034606989","time_class":"blitz","end_time":1608679921,"rated":true,"white":{"username":"KleegeChess","result":"checkmated"},"black":{"username":"colemartin99","result":"win"}},{"url":"https://www.chess.com/game/live/6034713395","time_class":"blitz","end_time":1608680927,"rated":true,"white":{"username":"blackburn3476","result":"resigned"},"black":{"username":"colemartin99","result":"win"}},{"url":"https://www.chess.com/game/live/6034737610","time_class":"blitz","end_time":1608681146,"rated":true,"white":{"username":"r01232","result":"resigned"},"black":{"username":"colemartin99","result":"win"}},{"url":"https://www.chess.com/game/live/6035067837","time_class":"blitz","end_time":1608684887,"rated":true,"white":{"username":"colemartin99","result":"timeout"},"black":{"username":"jackMehoff6969","result":"win"}},{"url":"https://www.chess.com/game/live/6035565457","time_class":"blitz","end_time":1608690991,"rated":true,"white":{"username":"colemartin99","result":"timevsinsufficient"},"black":{"username":"snugglepuffkins","result":"timevsinsufficient"}},{"url":"https://www.chess.com/game/live/6040878387","time_class":"blitz","end_time":1608749275,"rated":true,"white":{"username":"Asanali00","result":"timeout"},"black":{"username":"colemartin99","result":"win"}},{"url":"https://www.chess.com/game/live/6042203255","time_class":"blitz","end_time":1608759825,"rated":true,"white":{"username":"edotcarter","result":"resigned"},"black":{"username":"colemartin99","result":"win"}},{"url":"https://www.chess.com/game/live/6042233005","time_class":"blitz","end_time":1608760215,"rated":true,"white":{"username":"colemartin99","result":"timeout"},"black":{"username":"DonTiquila","result":"win"}},{"url":"https://www.chess.com/game/live/6043457739","time_class":"blitz","end_time":1608772231,"rated":true,"white":{"username":"Cosechador","result":"win"},"black":{"username":"colemartin99","result":"timeout"}},{"url":"https://www.chess.com/game/live/6043530087","time_class":"blitz","end_time":1608773120,"rated":true,"white":{"username":"BillParnell","result":"stalemate"},"black":{"username":"colemartin99","result":"stalemate"}},{"url":"https://www.chess.com/game/live/6043902679","time_class":"blitz","end_time":1608777577,"rated":true,"white":{"username":"colemartin99","result":"win"},"black":{"username":"joseaviles83","result":"checkmated"}},{"url":"https://www.chess.com/game/live/6043910005","time_class":"blitz","end_time":1608777910,"rated":true,"white":{"username":"colemartin99","result":"checkmated"},"black":{"username":"UberSnacks","result":"win"}},{"url":"https://www.chess.com/game/live/6044789664","time_class":"blitz","end_time":1608789957,"rated":true,"white":{"username":"colemartin99","result":"checkmated"},"black":{"username":"Lenci29","result":"win"}},{"url":"https://www.chess.com/game/live/6044814714","time_class":"blitz","end_time":1608790110,"rated":true,"white":{"username":"ViJuL2020","result":"win"},"black":{"username":"colemartin99","result":"checkmated"}},{"url":"https://www.chess.com/game/live/6044826015","time_class":"rapid","end_time":1608790688,"rated":true,"white":{"username":"colemartin99","result":"win"},"black":{"username":"samwisechess","result":"resigned"}},{"url":"https://www.chess.com/game/live/6044882997","time_class":"rapid","end_time":1608791828,"rated":true,"white":{"username":"aureussp","result":"checkmated"},"black":{"username":"colemartin99","result":"win"}},{"url":"https://www.chess.com/game/live/6044947955","time_class":"rapid","end_time":1608792892,"rated":true,"white":{"username":"ovrhere","result":"checkmated"},"black":{"username":"colemartin99","result":"win"}},{"url":"https://www.chess.com/game/live/6045029780","time_class":"rapid","end_time":1608793126,"rated":true,"white":{"username":"colemartin99","result":"win"},"black":{"username":"is414h","result":"resigned"}},{"url":"https://www.chess.com/game/live/6050111355","time_class":"blitz","end_time":1608843704,"rated":true,"white":{"username":"colemartin99","result":"stalemate"},"black":{"username":"apo6359","result":"stalemate"}},{"url":"https://www.chess.com/game/live/6050200406","time_class":"blitz","end_time":1608844259,"rated":true,"white":{"username":"spats78","result":"checkmated"},"black":{"username":"colemartin99","result":"win"}},{"url":"https://www.chess.com/game/live/6050213865","time_class":"blitz","end_time":1608844373,"rated":true,"white":{"username":"colemartin99","result":"win"},"black":{"username":"spats78","result":"checkmated"}},{"url":"https://www.chess.com/game/live/6050390168","time_class":"blitz","end_time":1608846127,"rated":true,"white":{"username":"TheShockerGuy","result":"resigned"},"black":{"username":"colemartin99","result":"win"}},{"url":"https://www.chess.com/game/live/6050592050","time_class":"blitz","end_time":1608848063,"rated":true,"white":{"username":"colemartin99","result":"win"},"black":{"username":"paulmorphy1111","result":"timeout"}},{"url":"https://www.chess.com/game/live/6050671309","time_class":"blitz","end_time":1608848763,"rated":true,"white":{"username":"colemartin99","result":"checkmated"},"black":{"username":"SanguchitoAmigable","result":"win"}},{"url":"https://www.chess.com/game/live/6051145717","time_class":"blitz","end_time":1608853689,"rated":true,"white":{"username":"colemartin99","result":"checkmated"},"black":{"username":"Belakorr","result":"win"}},{"url":"https://www.chess.com/game/live/6051645544","time_class":"blitz","end_time":1608859848,"rated":true,"white":{"username":"Muh0m0r4ik","result":"timeout"},"black":{"username":"colemartin99","result":"win"}},{"url":"https://www.chess.com/game/live/6051747191","time_class":"blitz","end_time":1608861200,"rated":true,"white":{"username":"T1velizkevin","result":"win"},"black":{"username":"colemartin99","result":"checkmated"}},{"url":"https://www.chess.com/game/live/6052584328","time_class":"blitz","end_time":1608873582,"rated":true,"white":{"username":"blee0507","result":"checkmated"},"black":{"username":"colemartin99","result":"win"}},{"url":"https://www.chess.com/game/live/6052612105","time_class":"blitz","end_time":1608874053,"rated":true,"white":{"username":"colemartin99","result":"timeout"},"black":{"username":"matthewd0806","result":"win"}},{"url":"https://www.chess.com/game/live/6053039213","time_class":"blitz","end_time":1608880441,"rated":true,"white":{"username":"colemartin99","result":"timeout"},"black":{"username":"ezzughayyar","result":"win"}},{"url":"https://www.chess.com/game/live/6053064626","time_class":"blitz","end_time":1608880665,"rated":true,"white":{"username":"colemartin99","result":"win"},"black":{"username":"NunuiBoy","result":"resigned"}},{"url":"https://www.chess.com/game/live/6053079606","time_class":"blitz","end_time":1608881074,"rated":true,"white":{"username":"Evil_Genuis_21MK","result":"timeout"},"black":{"username":"colemartin99","result":"win"}},{"url":"https://www.chess.com/game/live/6053106780","time_class":"blitz","end_time":1608881352,"rated":true,"white":{"username":"88rinoa88","result":"win"},"black":{"username":"colemartin99","result":"resigned"}},{"url":"https://www.chess.com/game/live/6055593010","time_class":"blitz","end_time":1608910718,"rated":true,"white":{"username":"joje2","result":"win"},"black":{"username":"colemartin99","result":"timeout"}},{"url":"https://www.chess.com/game/live/6055659623","time_class":"blitz","end_time":1608911242,"rated":true,"white":{"username":"colemartin99","result":"win"},"black":{"username":"Andrejketi","result":"checkmated"}},{"url":"https://www.chess.com/game/live/6055719272","time_class":"blitz","end_time":1608911627,"rated":true,"white":{"username":"colemartin99","result":"win"},"black":{"username":"Fedor_Sapronov","result":"abandoned"}},{"url":"https://www.chess.com/game/live/6056438934","time_class":"blitz","end_time":1608917969,"rated":true,"white":{"username":"colemartin99","result":"checkmated"},"black":{"username":"fapmax","result":"win"}},{"url":"https://www.chess.com/game/live/6058628471","time_class":"blitz","end_time":1608936695,"rated":true,"white":{"username":"Greengo95","result":"resigned"},"black":{"username":"colemartin99","result":"win"}},{"url":"https://www.chess.com/game/live/6058889704","time_class":"blitz","end_time":1608939123,"rated":true,"white":{"username":"LJx69","result":"win"},"black":{"username":"colemartin99","result":"checkmated"}},{"url":"https://www.chess.com/game/live/6060535304","time_class":"blitz","end_time":1608961056,"rated":true,"white":{"username":"colemartin99","result":"checkmated"},"black":{"username":"mdp202","result":"win"}},{"url":"https://www.chess.com/game/live/6060558346","time_class":"blitz","end_time":1608961391,"rated":true,"white":{"username":"colemartin99","result":"checkmated"},"black":{"username":"Aksaaja","result":"win"}},{"url":"https://www.chess.com/game/live/6060580358","time_class":"rapid","end_time":1608962313,"rated":true,"white":{"username":"colemartin99","result":"repetition"},"black":{"username":"anderplascencia","result":"repetition"}},{"url":"https://www.chess.com/game/live/6060640819","time_class":"rapid","end_time":1608962646,"rated":true,"white":{"username":"Rami_001","result":"win"},"black":{"username":"colemartin99","result":"abandoned"}},{"url":"https://www.chess.com/game/live/6065053400","time_class":"blitz","end_time":1609008676,"rated":true,"white":{"username":"colemartin99","result":"checkmated"},"black":{"username":"SSLane","result":"win"}},{"url":"https://www.chess.com/game/live/6065081126","time_class":"blitz","end_time":1609009013,"rated":true,"white":{"username":"ingMAFASE0308","result":"win"},"black":{"username":"colemartin99","result":"checkmated"}},{"url":"https://www.chess.com/game/live/6065123447","time_class":"blitz","end_time":1609009338,"rated":true,"white":{"username":"eyram_john","result":"resigned"},"black":{"username":"colemartin99","result":"win"}},{"url":"https://www.chess.com/game/live/6065164545","time_class":"blitz","end_time":1609009515,"rated":true,"white":{"username":"rhou6076","result":"checkmated"},"black":{"username":"colemartin99","result":"win"}},{"url":"https://www.chess.com/game/live/6068886394","time_class":"blitz","end_time":1609047750,"rated":true,"white":{"username":"colemartin99","result":"win"},"black":{"username":"PATATON2020","result":"timeout"}},{"url":"https://www.chess.com/game/live/6068911509","time_class":"blitz","end_time":1609048038,"rated":true,"white":{"username":"colemartin99","result":"insufficient"},"black":{"username":"olavfenne1","result":"insufficient"}},{"url":"https://www.chess.com/game/live/6068931432","time_class":"blitz","end_time":1609048330,"rated":true,"white":{"username":"EestiJuust","result":"checkmated"},"black":{"username":"colemartin99","result":"win"}},{"url":"https://www.chess.com/game/live/6068954079","time_class":"blitz","end_time":1609048731,"rated":true,"white":{"username":"OlympicCopy","result":"win"},"black":{"username":"colemartin99","result":"timeout"}},{"url":"https://www.chess.com/game/live/6068980382","time_class":"blitz","end_time":1609049138,"rated":true,"white":{"username":"colemartin99","result":"timeout"},"black":{"username":"birb232","result":"win"}},{"url":"https://www.chess.com/game/live/6069007580","time_class":"blitz","end_time":1609049534,"rated":true,"white":{"username":"GuyEO","result":"win"},"black":{"username":"colemartin99","result":"timeout"}},{"url":"https://www.chess.com/game/live/6069034911","time_class":"blitz","end_time":1609049904,"rated":true,"white":{"username":"BOSS_0009","result":"timeout"},"black":{"username":"colemartin99","result":"win"}},{"url":"https://www.chess.com/game/live/6075162208","time_class":"blitz","end_time":1609107226,"rated":true,"white":{"username":"colemartin99","result":"win"},"black":{"username":"Socr4tee","result":"timeout"}},{"url":"https://www.chess.com/game/live/6075206829","time_class":"blitz","end_time":1609107556,"rated":true,"white":{"username":"colemartin99","result":"timeout"},"black":{"username":"aborup","result":"win"}},{"url":"https://www.chess.com/game/live/6075246421","time_class":"blitz","end_time":1609107883,"rated":true,"white":{"username":"colemartin99","result":"win"},"black":{"username":"Maxwell","result":"checkmated"}},{"url":"https://www.chess.com/game/live/6075285560","time_class":"blitz","end_time":1609108136,"rated":true,"white":{"username":"ontherocksIam","result":"resigned"},"black":{"username":"colemartin99","result":"win"}},{"url":"https://www.chess.com/game/live/6075335700","time_class":"blitz","end_time":1609108585,"rated":true,"white":{"username":"colemartin99","result":"win"},"black":{"username":"bilguun0907","result":"checkmated"}},{"url":"https://www.chess.com/game/live/6075370952","time_class":"blitz","end_time":1609108971,"rated":true,"white":{"username":"colemartin99","result":"checkmated"},"black":{"username":"JeremyAmram","result":"win"}},{"url":"https://www.chess.com/game/live/6075866286","time_class":"blitz","end_time":1609113562,"rated":true,"white":{"username":"Mastorwin","result":"win"},"black":{"username":"colemartin99","result":"timeout"}},{"url":"https://www.chess.com/game/live/6092050300","time_class":"blitz","end_time":1609275515,"rated":true,"white":{"username":"jonathan1317","result":"win"},"black":{"username":"colemartin99","result":"timeout"}},{"url":"https://www.chess.com/game/live/6092416040","time_class":"blitz","end_time":1609278117,"rated":true,"white":{"username":"colemartin99","result":"win"},"black":{"username":"muderspach","result":"checkmated"}},{"url":"https://www.chess.com/game/live/6092443700","time_class":"blitz","end_time":1609278479,"rated":true,"white":{"username":"EliCobbs","result":"win"},"black":{"username":"colemartin99","result":"timeout"}},{"url":"https://www.chess.com/game/live/6093347904","time_class":"blitz","end_time":1609286008,"rated":true,"white":{"username":"KASRAF0","result":"win"},"black":{"username":"colemartin99","result":"abandoned"}},{"url":"https://www.chess.com/game/live/6093837266","time_class":"blitz","end_time":1609290989,"rated":true,"white":{"username":"GK72","result":"win"},"black":{"username":"colemartin99","result":"checkmated"}},{"url":"https://www.chess.com/game/live/6093851830","time_class":"rapid","end_time":1609291736,"rated":true,"white":{"username":"colemartin99","result":"win"},"black":{"username":"JSD04","result":"checkmated"}},{"url":"https://www.chess.com/game/live/6093938157","time_class":"rapid","end_time":1609292380,"rated":true,"white":{"username":"colemartin99","result":"win"},"black":{"username":"MBKchesser","result":"checkmated"}},{"url":"https://www.chess.com/game/live/6094556817","time_class":"rapid","end_time":1609299719,"rated":true,"white":{"username":"DECO696","result":"win"},"black":{"username":"colemartin99","result":"checkmated"}},{"url":"https://www.chess.com/game/live/6094608065","time_class":"rapid","end_time":1609300243,"rated":true,"white":{"username":"colemartin99","result":"win"},"black":{"username":"GeorgeAmza","result":"checkmated"}},{"url":"https://www.chess.com/game/live/6094653993","time_class":"rapid","end_time":1609301413,"rated":true,"white":{"username":"colemartin99","result":"checkmated"},"black":{"username":"Moises464","result":"win"}},{"url":"https://www.chess.com/game/live/6095327098","time_class":"rapid","end_time":1609310153,"rated":true,"white":{"username":"WombatCombat27","result":"win"},"black":{"username":"colemartin99","result":"checkmated"}},{"url":"https://www.chess.com/game/live/6095383739","time_class":"rapid","end_time":1609310292,"rated":true,"white":{"username":"rakeshyadav1","result":"win"},"black":{"username":"colemartin99","result":"abandoned"}},{"url":"https://www.chess.com/game/live/6098576674","time_class":"blitz","end_time":1609344671,"rated":true,"white":{"username":"colemartin99","result":"checkmated"},"black":{"username":"braisesdusud","result":"win"}},{"url":"https://www.chess.com/game/live/6098621301","time_class":"blitz","end_time":1609345023,"rated":true,"white":{"username":"GokuRushi","result":"stalemate"},"black":{"username":"colemartin99","result":"stalemate"}},{"url":"https://www.chess.com/game/live/6098675907","time_class":"blitz","end_time":1609345397,"rated":true,"white":{"username":"colemartin99","result":"checkmated"},"black":{"username":"eclaihootn","result":"win"}},{"url":"https://www.chess.com/game/live/6098743510","time_class":"blitz","end_time":1609345709,"rated":true,"white":{"username":"kalikamana","result":"win"},"black":{"username":"colemartin99","result":"resigned"}},{"url":"https://www.chess.com/game/live/6099364193","time_class":"blitz","end_time":1609350684,"rated":true,"white":{"username":"colemartin99","result":"timeout"},"black":{"username":"ettenro","result":"win"}},{"url":"https://www.chess.com/game/live/6099426167","time_class":"rapid","end_time":1609351155,"rated":true,"white":{"username":"RustySa","result":"resigned"},"black":{"username":"colemartin99","result":"win"}},{"url":"https://www.chess.com/game/live/6099623156","time_class":"rapid","end_time":1609353303,"rated":true,"white":{"username":"tarun4279","result":"win"},"black":{"username":"colemartin99","result":"checkmated"}},{"url":"https://www.chess.com/game/live/6103837492","time_class":"blitz","end_time":1609392221,"rated":true,"white":{"username":"colemartin99","result":"win"},"black":{"username":"illywonka","result":"timeout"}},{"url":"https://www.chess.com/game/live/6106440489","time_class":"blitz","end_time":1609422880,"rated":true,"white":{"username":"colemartin99","result":"win"},"black":{"username":"Harsh4883","result":"resigned"}},{"url":"https://www.chess.com/game/live/6106473400","time_class":"blitz","end_time":1609423221,"rated":true,"white":{"username":"colemartin99","result":"win"},"black":{"username":"r2i2b2u2","result":"checkmated"}},{"url":"https://www.chess.com/game/live/6106506259","time_class":"blitz","end_time":1609423561,"rated":true,"white":{"username":"diputhenoob7","result":"resigned"},"black":{"username":"colemartin99","result":"win"}},{"url":"https://www.chess.com/game/live/6106664306","time_class":"blitz","end_time":1609425076,"rated":true,"white":{"username":"Peacock-Penguin","result":"checkmated"},"black":{"username":"colemartin99","result":"win"}},{"url":"https://www.chess.com/game/live/6106707880","time_class":"blitz","end_time":1609425522,"rated":true,"white":{"username":"colemartin99","result":"timeout"},"black":{"username":"Keshbansal","result":"win"}},{"url":"https://www.chess.com/game/live/6107057682","time_class":"blitz","end_time":1609428470,"rated":true,"white":{"username":"colemartin99","result":"timeout"},"black":{"username":"sanketjshah","result":"win"}},{"url":"https://www.chess.com/game/live/6107461065","time_class":"blitz","end_time":1609431819,"rated":true,"white":{"username":"max3618","result":"checkmated"},"black":{"username":"colemartin99","result":"win"}},{"url":"https://www.chess.com/game/live/6110432687","time_class":"blitz","end_time":1609458815,"rated":true,"white":{"username":"mephistoDpheles","result":"win"},"black":{"username":"colemartin99","result":"checkmated"}}]